{
	"name": "DF_title",
	"properties": {
		"type": "MappingDataFlow",
		"typeProperties": {
			"sources": [
				{
					"dataset": {
						"referenceName": "DF_Tgt_table",
						"type": "DatasetReference"
					},
					"name": "source1"
				}
			],
			"sinks": [],
			"transformations": [],
			"scriptLines": [
				"source(output(",
				"          title_id as string,",
				"          title as string,",
				"          type as string,",
				"          pub_id as string,",
				"          price as string,",
				"          notes as string,",
				"          pubdate as string",
				"     ),",
				"     allowSchemaDrift: true,",
				"     validateSchema: false,",
				"     isolationLevel: 'READ_UNCOMMITTED',",
				"     format: 'table') ~> source1"
			]
		}
	}
}