{
	"name": "PL_Day02_04_IN1709",
	"properties": {
		"activities": [
			{
				"name": "Get Metadata1",
				"type": "GetMetadata",
				"dependsOn": [],
				"policy": {
					"timeout": "0.12:00:00",
					"retry": 0,
					"retryIntervalInSeconds": 30,
					"secureOutput": false,
					"secureInput": false
				},
				"userProperties": [],
				"typeProperties": {
					"dataset": {
						"referenceName": "DelimitedText3",
						"type": "DatasetReference"
					},
					"fieldList": [
						"itemName"
					],
					"storeSettings": {
						"type": "AzureBlobStorageReadSettings",
						"enablePartitionDiscovery": false
					},
					"formatSettings": {
						"type": "DelimitedTextReadSettings"
					}
				}
			},
			{
				"name": "If Condition1",
				"type": "IfCondition",
				"dependsOn": [
					{
						"activity": "Get Metadata1",
						"dependencyConditions": [
							"Succeeded"
						]
					}
				],
				"userProperties": [],
				"typeProperties": {
					"expression": {
						"value": "@endswith(activity('Get Metadata1').output.itemName,'.csv')",
						"type": "Expression"
					},
					"ifFalseActivities": [
						{
							"name": "Fail1",
							"type": "Fail",
							"dependsOn": [],
							"userProperties": [],
							"typeProperties": {
								"message": "This is not Supported file",
								"errorCode": "404"
							}
						}
					],
					"ifTrueActivities": [
						{
							"name": "Wait1",
							"type": "Wait",
							"dependsOn": [],
							"userProperties": [],
							"typeProperties": {
								"waitTimeInSeconds": 1
							}
						}
					]
				}
			}
		],
		"folder": {
			"name": "Day2"
		},
		"annotations": []
	}
}