{
	"name": "PL_exercise_3_IN1725_2",
	"properties": {
		"activities": [
			{
				"name": "Lookup1",
				"type": "Lookup",
				"dependsOn": [],
				"policy": {
					"timeout": "0.12:00:00",
					"retry": 0,
					"retryIntervalInSeconds": 30,
					"secureOutput": false,
					"secureInput": false
				},
				"userProperties": [],
				"typeProperties": {
					"source": {
						"type": "DelimitedTextSource",
						"storeSettings": {
							"type": "AzureBlobStorageReadSettings",
							"recursive": true,
							"enablePartitionDiscovery": false
						},
						"formatSettings": {
							"type": "DelimitedTextReadSettings"
						}
					},
					"dataset": {
						"referenceName": "DelimitedText1",
						"type": "DatasetReference",
						"parameters": {
							"p_file_name": "Sales.csv",
							"P_directory": "sales",
							"P_container": "input"
						}
					},
					"firstRowOnly": false
				}
			},
			{
				"name": "ForEach1",
				"type": "ForEach",
				"dependsOn": [
					{
						"activity": "Lookup1",
						"dependencyConditions": [
							"Completed"
						]
					}
				],
				"userProperties": [],
				"typeProperties": {
					"items": {
						"value": "@activity('Lookup1').output.value",
						"type": "Expression"
					},
					"isSequential": false,
					"activities": [
						{
							"name": "If Condition1",
							"type": "IfCondition",
							"dependsOn": [],
							"userProperties": [],
							"typeProperties": {
								"expression": {
									"value": "@and(not(equals(item().LocationName, null)), not(equals(trim(item().LocationName), '')))",
									"type": "Expression"
								}
							}
						},
						{
							"name": "Execute Pipeline1",
							"type": "ExecutePipeline",
							"dependsOn": [
								{
									"activity": "If Condition1",
									"dependencyConditions": [
										"Succeeded"
									]
								}
							],
							"policy": {
								"secureInput": false
							},
							"userProperties": [],
							"typeProperties": {
								"pipeline": {
									"referenceName": "PL_exercise_3_IN1725_2_child",
									"type": "PipelineReference"
								},
								"waitOnCompletion": true,
								"parameters": {
									"locationname": {
										"value": "@item().locationname",
										"type": "Expression"
									}
								}
							}
						}
					]
				}
			}
		],
		"folder": {
			"name": "DAY 3 Exercise"
		},
		"annotations": []
	}
}