{
	"name": "PL_SCD_2",
	"properties": {
		"activities": [
			{
				"name": "Data flow1",
				"type": "ExecuteDataFlow",
				"dependsOn": [],
				"policy": {
					"timeout": "0.12:00:00",
					"retry": 0,
					"retryIntervalInSeconds": 30,
					"secureOutput": false,
					"secureInput": false
				},
				"userProperties": [],
				"typeProperties": {
					"dataflow": {
						"referenceName": "DS_SCD_2P",
						"type": "DataFlowReference",
						"datasetParameters": {
							"source1": {
								"tablename": "source_scd2"
							},
							"source2": {
								"tablename": "target_scd2"
							},
							"sink1": {
								"tablename": "target_scd2"
							},
							"sink2": {
								"tablename": "target_scd2"
							}
						}
					},
					"compute": {
						"coreCount": 8,
						"computeType": "General"
					},
					"traceLevel": "Fine"
				}
			}
		],
		"folder": {
			"name": "Workshop"
		},
		"annotations": []
	}
}